LICENSE.txt
MANIFEST.in
README.md
requirements.txt
run-pipeline
run-pipeline2
run-pipeline3
run-warrior
run-warrior2
run-warrior3
setup.py
doc/Makefile
doc/conf.py
doc/index.rst
doc/make.bat
doc/api/seesaw.rst
examples/example-pipeline.py
examples/picplz-example-pipeline.py
examples/picplz-example.py
seesaw/__init__.py
seesaw/config.py
seesaw/event.py
seesaw/externalprocess.py
seesaw/externalprocess_test.py
seesaw/init_test.py
seesaw/item.py
seesaw/item_test.py
seesaw/log.py
seesaw/pipeline.py
seesaw/pipeline_test.py
seesaw/project.py
seesaw/runner.py
seesaw/runner_test.py
seesaw/six.py
seesaw/task.py
seesaw/test_base.py
seesaw/tracker.py
seesaw/util.py
seesaw/util_test.py
seesaw/warrior.py
seesaw/web.py
seesaw/web_util.py
seesaw.egg-info/PKG-INFO
seesaw.egg-info/SOURCES.txt
seesaw.egg-info/dependency_links.txt
seesaw.egg-info/requires.txt
seesaw.egg-info/top_level.txt
seesaw/public/index.html
seesaw/public/jquery-1.12.4.min.js
seesaw/public/reset.css
seesaw/public/script.js
seesaw/public/smoothie.js
seesaw/public/sockjs-0.3.js
seesaw/public/style.css
seesaw/public/warrior-logo.png
seesaw/script/__init__.py
seesaw/script/run_pipeline.py
seesaw/script/run_warrior.py
seesaw/templates/all-projects.html
seesaw/templates/help.html
seesaw/templates/settings.html
tests/hq_mock.py
tests/run_pipeline_test.py
tests/run_warrior_local.py