Metadata-Version: 2.1
Name: seesaw
Version: 0.10.3
Summary: ArchiveTeam seesaw kit
Home-page: http://www.archiveteam.org/
Maintainer: ArchiveTeam
Maintainer-email: warrior@archiveteam.org
License: UNKNOWN
Platform: UNKNOWN
